<?xml version="1.0"?>
<!-- Written on 16-Jun-2010 13:09:49 using the XML Toolbox for Matlab -->
<root xml_tb_version="3.1" idx="1" type="struct" size="1 1">
  <filename idx="1" type="char" size="1 24">Purpure_by_miss_mosh.jpg</filename>
  <features idx="1" type="struct" size="1 1">
    <numFaces idx="1" type="struct" size="1 1">
      <data idx="1" type="double" size="1 1">1</data>
    </numFaces>
    <cornerRatio idx="1" type="struct" size="1 1">
      <data idx="1" type="double" size="1 1">0.0003296296296296296</data>
    </cornerRatio>
    <edgeRatio idx="1" type="struct" size="1 1">
      <data idx="1" type="double" size="1 1">0.06816296296296297</data>
    </edgeRatio>
    <gridEdgeRatio idx="1" type="struct" size="1 1">
      <data idx="1" type="double" size="1 9">0.03031354853638795 0.06102378473083095 0.02360465116279072 0.1629890415034463 0.05151980958992414 0.0710299003322259 0.08053067993366494 0.07107794361525704 0.06003333333333328</data>
    </gridEdgeRatio>
    <medianHue idx="1" type="struct" size="1 1">
      <data idx="1" type="double" size="1 1">10</data>
    </medianHue>
    <avgSat idx="1" type="struct" size="1 1">
      <data idx="1" type="double" size="1 1">78.35431851851847</data>
    </avgSat>
    <avgInt idx="1" type="struct" size="1 1">
      <data idx="1" type="double" size="1 1">195.6508333333336</data>
    </avgInt>
    <medHueCells idx="1" type="struct" size="1 1">
      <data idx="1" type="double" size="1 9">1 8 9 17 8 6 13 11 11</data>
    </medHueCells>
    <avgSatCells idx="1" type="struct" size="1 1">
      <data idx="1" type="double" size="1 9">48.03942083601923 87.67141038991096 103.9507794361526 41.3376473116147 71.06657741194357 125.0230514096185 38.60926910299004 75.41491694352153 113.9626333333333</data>
    </avgSatCells>
    <avgIntCells idx="1" type="struct" size="1 1">
      <data idx="1" type="double" size="1 9">233.0153551180972 175.2432025916927 162.9896351575456 236.3209864299762 208.8180030082146 154.2026036484245 235.172142857143 195.9769601328904 159.1323</data>
    </avgIntCells>
    <cornerRatioGrid idx="1" type="struct" size="1 1">
      <data idx="1" type="double" size="1 9">12 42 0 54 17 5 20 14 14</data>
    </cornerRatioGrid>
    <avgR idx="1" type="struct" size="1 1">
      <data idx="1" type="double" size="1 1">195.611566666667</data>
    </avgR>
    <avgG idx="1" type="struct" size="1 1">
      <data idx="1" type="double" size="1 1">161.9710444444445</data>
    </avgG>
    <avgB idx="1" type="struct" size="1 1">
      <data idx="1" type="double" size="1 1">149.0941351851853</data>
    </avgB>
    <avgRCells idx="1" type="struct" size="1 1">
      <data idx="1" type="double" size="1 9">232.9674054974298 175.2135501892531 162.9761857379768 236.1159650253714 208.7735905191649 154.1972305140961 235.172142857143 195.9769601328904 159.12605</data>
    </avgRCells>
    <avgGCells idx="1" type="struct" size="1 1">
      <data idx="1" type="double" size="1 9">204.4172493016645 140.704434637444 119.8314427860697 218.6779392076164 173.0876679724302 104.6003648424544 215.3591196013289 163.1684219269104 117.9724166666667</data>
    </avgGCells>
    <avgBCells idx="1" type="struct" size="1 1">
      <data idx="1" type="double" size="1 9">196.9494388522504 127.4664881572206 108.8762354892206 204.9726946662039 162.6983520933538 92.53834162520725 200.3168106312293 145.3219933554817 102.7514</data>
    </avgBCells>
    <intEntropy idx="1" type="struct" size="1 1">
      <data idx="1" type="double" size="1 1">7.51885981083893</data>
    </intEntropy>
    <intVariance idx="1" type="struct" size="1 1">
      <data idx="1" type="double" size="1 1">5057.599093762686</data>
    </intVariance>
  </features>
</root>
