<?xml version="1.0"?>
<!-- Written on 16-Jun-2010 13:11:58 using the XML Toolbox for Matlab -->
<root xml_tb_version="3.1" idx="1" type="struct" size="1 1">
  <filename idx="1" type="char" size="1 30">eviva_l__arte_by_Mentosik8.jpg</filename>
  <features idx="1" type="struct" size="1 1">
    <numFaces idx="1" type="struct" size="1 1">
      <data idx="1" type="double" size="1 1">0</data>
    </numFaces>
    <cornerRatio idx="1" type="struct" size="1 1">
      <data idx="1" type="double" size="1 1">0.0001461262751585332</data>
    </cornerRatio>
    <edgeRatio idx="1" type="struct" size="1 1">
      <data idx="1" type="double" size="1 1">0.02283613638452348</data>
    </edgeRatio>
    <gridEdgeRatio idx="1" type="struct" size="1 1">
      <data idx="1" type="double" size="1 9">0.01453077201407845 0.01143054504786025 0 0.02195651458833588 0.1034669912173942 0.01208745874587458 0.009958533589441298 0.02079915583291429 0.01113316790736146</data>
    </gridEdgeRatio>
    <medianHue idx="1" type="struct" size="1 1">
      <data idx="1" type="double" size="1 1">13</data>
    </medianHue>
    <avgSat idx="1" type="struct" size="1 1">
      <data idx="1" type="double" size="1 1">107.313425236651</data>
    </avgSat>
    <avgInt idx="1" type="struct" size="1 1">
      <data idx="1" type="double" size="1 1">96.20196397389955</data>
    </avgInt>
    <medHueCells idx="1" type="struct" size="1 1">
      <data idx="1" type="double" size="1 9">11 11 30 15 13 16 11 11 14</data>
    </medHueCells>
    <avgSatCells idx="1" type="struct" size="1 1">
      <data idx="1" type="double" size="1 9">69.46497648103679 78.5727360942074 76.34623216243622 126.5515936975759 120.3569290483866 102.4152081976537 139.6643729372937 158.4279785478547 94.71499586435067</data>
    </avgSatCells>
    <avgIntCells idx="1" type="struct" size="1 1">
      <data idx="1" type="double" size="1 9">118.9008420775632 81.90688628663527 47.32374302366797 166.9964968257623 80.16932008815496 48.49977329497212 143.1551980198019 114.248209570957 64.7029363110008</data>
    </avgIntCells>
    <cornerRatioGrid idx="1" type="struct" size="1 1">
      <data idx="1" type="double" size="1 9">24 10 0 8 91 6 2 16 2</data>
    </cornerRatioGrid>
    <avgR idx="1" type="struct" size="1 1">
      <data idx="1" type="double" size="1 1">95.1217296204393</data>
    </avgR>
    <avgG idx="1" type="struct" size="1 1">
      <data idx="1" type="double" size="1 1">74.23010936494805</data>
    </avgG>
    <avgB idx="1" type="struct" size="1 1">
      <data idx="1" type="double" size="1 1">53.10318904512449</data>
    </avgB>
    <avgRCells idx="1" type="struct" size="1 1">
      <data idx="1" type="double" size="1 9">118.9008420775632 80.43805302457153 42.67175585105068 166.9964968257623 80.16921318377683 44.90632548246951 143.1551980198019 114.248209570957 64.7029363110008</data>
    </avgRCells>
    <avgGCells idx="1" type="struct" size="1 1">
      <data idx="1" type="double" size="1 9">95.06924936679717 65.31644518272427 43.71474736816076 132.2558304003158 58.95240288148416 41.3584000395703 103.190891089109 74.31174917491754 53.8777171215881</data>
    </avgGCells>
    <avgBCells idx="1" type="struct" size="1 1">
      <data idx="1" type="double" size="1 9">85.73563369625994 56.08051544357092 32.50794291979587 84.92600572349598 39.68870267425412 28.61099890357202 65.69394389438939 43.20136138613864 41.24662531017366</data>
    </avgBCells>
    <intEntropy idx="1" type="struct" size="1 1">
      <data idx="1" type="double" size="1 1">7.035333141948259</data>
    </intEntropy>
    <intVariance idx="1" type="struct" size="1 1">
      <data idx="1" type="double" size="1 1">2445.687198817429</data>
    </intVariance>
  </features>
</root>
