<?xml version="1.0"?>
<!-- Written on 16-Jun-2010 13:08:42 using the XML Toolbox for Matlab -->
<root xml_tb_version="3.1" idx="1" type="struct" size="1 1">
  <filename idx="1" type="char" size="1 53">I__ve_been_treated_so_wrong___by_hybridinsurgency.jpg</filename>
  <features idx="1" type="struct" size="1 1">
    <numFaces idx="1" type="struct" size="1 1">
      <data idx="1" type="double" size="1 1">0</data>
    </numFaces>
    <cornerRatio idx="1" type="struct" size="1 1">
      <data idx="1" type="double" size="1 1">0.0001557952405410033</data>
    </cornerRatio>
    <edgeRatio idx="1" type="struct" size="1 1">
      <data idx="1" type="double" size="1 1">0.04930662557781202</data>
    </edgeRatio>
    <gridEdgeRatio idx="1" type="struct" size="1 1">
      <data idx="1" type="double" size="1 9">0.04493470306352099 0.0582390495583078 0.04801843317972356 0.05369199442717823 0.07870845262335971 0.018678955453149 0.02262810600609337 0.07749896657837942 0.04135176651305674</data>
    </gridEdgeRatio>
    <medianHue idx="1" type="struct" size="1 1">
      <data idx="1" type="double" size="1 1">100</data>
    </medianHue>
    <avgSat idx="1" type="struct" size="1 1">
      <data idx="1" type="double" size="1 1">119.2584078068824</data>
    </avgSat>
    <avgInt idx="1" type="struct" size="1 1">
      <data idx="1" type="double" size="1 1">168.0193888032874</data>
    </avgInt>
    <medHueCells idx="1" type="struct" size="1 1">
      <data idx="1" type="double" size="1 9">104 106 30 100 104 115 11 8 21</data>
    </medHueCells>
    <avgSatCells idx="1" type="struct" size="1 1">
      <data idx="1" type="double" size="1 9">183.8678904419981 150.6847222009584 53.35756388076612 144.6531530841895 151.4256931579833 97.13958081357075 69.73574500768045 104.1570967741936 117.8190783410139</data>
    </avgSatCells>
    <avgIntCells idx="1" type="struct" size="1 1">
      <data idx="1" type="double" size="1 9">198.3374312965995 156.6381799531515 198.4569101459038 206.4215441615506 178.5950518241805 146.8446652479445 224.7615207373272 97.88462365591397 103.605529953917</data>
    </avgIntCells>
    <cornerRatioGrid idx="1" type="struct" size="1 1">
      <data idx="1" type="double" size="1 9">0 20 21 0 13 0 3 34 0</data>
    </cornerRatioGrid>
    <avgR idx="1" type="struct" size="1 1">
      <data idx="1" type="double" size="1 1">133.4607892484165</data>
    </avgR>
    <avgG idx="1" type="struct" size="1 1">
      <data idx="1" type="double" size="1 1">113.3520698510528</data>
    </avgG>
    <avgB idx="1" type="struct" size="1 1">
      <data idx="1" type="double" size="1 1">130.1168173258004</data>
    </avgB>
    <avgRCells idx="1" type="struct" size="1 1">
      <data idx="1" type="double" size="1 9">146.7854463615903 80.71287719889155 183.1742425402268 171.2164980020515 110.273236676516 114.9663793499396 224.2132565284179 96.39422427035333 73.22095238095243</data>
    </avgRCells>
    <avgGCells idx="1" type="struct" size="1 1">
      <data idx="1" type="double" size="1 9">93.33648207970364 97.5670499257467 176.5268306872637 117.3982730376472 109.5656873402024 110.6309842766814 184.2926420890939 66.01682027649767 64.47135176651307</data>
    </avgGCells>
    <avgBCells idx="1" type="struct" size="1 1">
      <data idx="1" type="double" size="1 9">115.3936035029166 143.7220478589034 187.6272027190471 140.4825696219973 146.9603931595144 128.5159759327586 168.7295084485407 56.22912442396312 82.9768817204301</data>
    </avgBCells>
    <intEntropy idx="1" type="struct" size="1 1">
      <data idx="1" type="double" size="1 1">6.563929394867285</data>
    </intEntropy>
    <intVariance idx="1" type="struct" size="1 1">
      <data idx="1" type="double" size="1 1">5143.178708180352</data>
    </intVariance>
  </features>
</root>
