<?xml version="1.0"?>
<!-- Written on 16-Jun-2010 13:09:06 using the XML Toolbox for Matlab -->
<root xml_tb_version="3.1" idx="1" type="struct" size="1 1">
  <filename idx="1" type="char" size="1 21">Lure_by_wirestyle.jpg</filename>
  <features idx="1" type="struct" size="1 1">
    <numFaces idx="1" type="struct" size="1 1">
      <data idx="1" type="double" size="1 1">0</data>
    </numFaces>
    <cornerRatio idx="1" type="struct" size="1 1">
      <data idx="1" type="double" size="1 1">0.001364653243847875</data>
    </cornerRatio>
    <edgeRatio idx="1" type="struct" size="1 1">
      <data idx="1" type="double" size="1 1">0.1121029082774049</data>
    </edgeRatio>
    <gridEdgeRatio idx="1" type="struct" size="1 1">
      <data idx="1" type="double" size="1 9">0.01698175787728027 0.1909121061359867 0.1932333333333334 0.01313432835820896 0.1846766169154228 0.1313 0.03405789842732644 0.1656148786269993 0.08033557046979867</data>
    </gridEdgeRatio>
    <medianHue idx="1" type="struct" size="1 1">
      <data idx="1" type="double" size="1 1">25</data>
    </medianHue>
    <avgSat idx="1" type="struct" size="1 1">
      <data idx="1" type="double" size="1 1">60.76812826249067</data>
    </avgSat>
    <avgInt idx="1" type="struct" size="1 1">
      <data idx="1" type="double" size="1 1">96.55220730797906</data>
    </avgInt>
    <medHueCells idx="1" type="struct" size="1 1">
      <data idx="1" type="double" size="1 9">0 120 120 22 30 18 25 21 88</data>
    </medHueCells>
    <avgSatCells idx="1" type="struct" size="1 1">
      <data idx="1" type="double" size="1 9">11.28776119402985 40.33386401326699 59.70453103609467 62.92961857379771 88.7678606965174 122.3926341447126 51.00656666666668 54.84953333333335 56.69073825503354</data>
    </avgSatCells>
    <avgIntCells idx="1" type="struct" size="1 1">
      <data idx="1" type="double" size="1 9">25.48597014925373 28.62013266998341 44.93632508597949 122.707728026534 158.2678275290216 176.4544058232327 141.4824 103.3860666666667 68.76154362416109</data>
    </avgIntCells>
    <cornerRatioGrid idx="1" type="struct" size="1 1">
      <data idx="1" type="double" size="1 9">10 55 62 4 60 56 18 38 63</data>
    </cornerRatioGrid>
    <avgR idx="1" type="struct" size="1 1">
      <data idx="1" type="double" size="1 1">93.03536912751674</data>
    </avgR>
    <avgG idx="1" type="struct" size="1 1">
      <data idx="1" type="double" size="1 1">77.04684563758396</data>
    </avgG>
    <avgB idx="1" type="struct" size="1 1">
      <data idx="1" type="double" size="1 1">69.72288590604026</data>
    </avgB>
    <avgRCells idx="1" type="struct" size="1 1">
      <data idx="1" type="double" size="1 9">23.75266998341624 24.40036484245439 40.66379511836789 119.3409950248756 154.5579767827529 174.7399245383817 136.4541999999999 100.8801333333333 63.63244966442955</data>
    </avgRCells>
    <avgGCells idx="1" type="struct" size="1 1">
      <data idx="1" type="double" size="1 9">24.51797678275291 23.51691542288559 31.55911716584861 101.9461028192371 124.3132006633499 117.5820561621424 130.1919666666666 84.52406666666666 55.71503355704694</data>
    </avgGCells>
    <avgBCells idx="1" type="struct" size="1 1">
      <data idx="1" type="double" size="1 9">25.18132669983416 28.06696517412935 35.98430665464623 90.51051409618574 110.4746600331675 94.90821062472875 113.4469333333333 75.05720000000001 54.3980201342282</data>
    </avgBCells>
    <intEntropy idx="1" type="struct" size="1 1">
      <data idx="1" type="double" size="1 1">6.093729724543411</data>
    </intEntropy>
    <intVariance idx="1" type="struct" size="1 1">
      <data idx="1" type="double" size="1 1">6107.823049084529</data>
    </intVariance>
  </features>
</root>
