<?xml version="1.0"?>
<!-- Written on 16-Jun-2010 13:09:06 using the XML Toolbox for Matlab -->
<root xml_tb_version="3.1" idx="1" type="struct" size="1 1">
  <filename idx="1" type="char" size="1 29">Lurking_Shadow_by_Skarbog.jpg</filename>
  <features idx="1" type="struct" size="1 1">
    <numFaces idx="1" type="struct" size="1 1">
      <data idx="1" type="double" size="1 1">0</data>
    </numFaces>
    <cornerRatio idx="1" type="struct" size="1 1">
      <data idx="1" type="double" size="1 1">0.0004530542102796438</data>
    </cornerRatio>
    <edgeRatio idx="1" type="struct" size="1 1">
      <data idx="1" type="double" size="1 1">0.1246523980628027</data>
    </edgeRatio>
    <gridEdgeRatio idx="1" type="struct" size="1 1">
      <data idx="1" type="double" size="1 9">0.2530589543937708 0.2550055617352613 0.1053948832035596 0.1085465331850204 0.1502595476455321 0.1381627734519836 0.02796942010068993 0.01039530113742309 0.07332649636397538</data>
    </gridEdgeRatio>
    <medianHue idx="1" type="struct" size="1 1">
      <data idx="1" type="double" size="1 1">24</data>
    </medianHue>
    <avgSat idx="1" type="struct" size="1 1">
      <data idx="1" type="double" size="1 1">27.48483570275477</data>
    </avgSat>
    <avgInt idx="1" type="struct" size="1 1">
      <data idx="1" type="double" size="1 1">54.61793469770342</data>
    </avgInt>
    <medHueCells idx="1" type="struct" size="1 1">
      <data idx="1" type="double" size="1 9">42 24 0 25 24 24 25 24 24</data>
    </medHueCells>
    <avgSatCells idx="1" type="struct" size="1 1">
      <data idx="1" type="double" size="1 9">19.93766221727846 25.32730812013348 19.80929517061347 17.93919169447535 43.01733407489802 57.84243893343279 17.30408787541713 34.51877085650723 12.27400708558643</data>
    </avgSatCells>
    <avgIntCells idx="1" type="struct" size="1 1">
      <data idx="1" type="double" size="1 9">91.78369484612529 44.77104189840563 12.16413388029089 85.33064516129032 60.95851872450869 19.99701659518925 59.74578235076009 55.95995550611792 60.88816893529741</data>
    </avgIntCells>
    <cornerRatioGrid idx="1" type="struct" size="1 1">
      <data idx="1" type="double" size="1 9">10 28 7 7 27 6 1 1 0</data>
    </cornerRatioGrid>
    <avgR idx="1" type="struct" size="1 1">
      <data idx="1" type="double" size="1 1">53.69758891839815</data>
    </avgR>
    <avgG idx="1" type="struct" size="1 1">
      <data idx="1" type="double" size="1 1">53.27268655939179</data>
    </avgG>
    <avgB idx="1" type="struct" size="1 1">
      <data idx="1" type="double" size="1 1">50.90968077904492</data>
    </avgB>
    <avgRCells idx="1" type="struct" size="1 1">
      <data idx="1" type="double" size="1 9">85.50857434186132 44.66050241008528 12.11294984150662 84.80107526881721 60.93033926585092 19.99412642177885 59.23975713756025 55.61897478680016 60.52055752377399</data>
    </avgRCells>
    <avgGCells idx="1" type="struct" size="1 1">
      <data idx="1" type="double" size="1 9">87.35771227289577 44.12671486837228 11.86099198209957 83.97432332220986 59.065489432703 19.27386723848592 58.98748609566184 54.55005561735261 60.3196904717509</data>
    </avgGCells>
    <avgBCells idx="1" type="struct" size="1 1">
      <data idx="1" type="double" size="1 9">89.71116054875789 40.95105672969967 10.92271116912176 80.27558398220246 54.15373563218392 16.84006153272422 56.29338153503891 50.61420096403413 58.39362297221702</data>
    </avgBCells>
    <intEntropy idx="1" type="struct" size="1 1">
      <data idx="1" type="double" size="1 1">6.990247800209759</data>
    </intEntropy>
    <intVariance idx="1" type="struct" size="1 1">
      <data idx="1" type="double" size="1 1">1366.543909520987</data>
    </intVariance>
  </features>
</root>
