<?xml version="1.0"?>
<!-- Written on 16-Jun-2010 13:12:29 using the XML Toolbox for Matlab -->
<root xml_tb_version="3.1" idx="1" type="struct" size="1 1">
  <filename idx="1" type="char" size="1 33">on_my_throne_by_Kitsunebaka91.jpg</filename>
  <features idx="1" type="struct" size="1 1">
    <numFaces idx="1" type="struct" size="1 1">
      <data idx="1" type="double" size="1 1">2</data>
    </numFaces>
    <cornerRatio idx="1" type="struct" size="1 1">
      <data idx="1" type="double" size="1 1">0.001112172489082969</data>
    </cornerRatio>
    <edgeRatio idx="1" type="struct" size="1 1">
      <data idx="1" type="double" size="1 1">0.1666024153930131</data>
    </edgeRatio>
    <gridEdgeRatio idx="1" type="struct" size="1 1">
      <data idx="1" type="double" size="1 9">0.05886170667644005 0.2221840449575469 0.05259443370462442 0.1322536802883146 0.3519103903243538 0.2827257663628829 0.1089044652128764 0.1620548530938856 0.1300438798367549</data>
    </gridEdgeRatio>
    <medianHue idx="1" type="struct" size="1 1">
      <data idx="1" type="double" size="1 1">3</data>
    </medianHue>
    <avgSat idx="1" type="struct" size="1 1">
      <data idx="1" type="double" size="1 1">17.00682911435591</data>
    </avgSat>
    <avgInt idx="1" type="struct" size="1 1">
      <data idx="1" type="double" size="1 1">220.0914318367908</data>
    </avgInt>
    <medHueCells idx="1" type="struct" size="1 1">
      <data idx="1" type="double" size="1 9">0 0 0 8 6 8 0 6 2</data>
    </medHueCells>
    <avgSatCells idx="1" type="struct" size="1 1">
      <data idx="1" type="double" size="1 9">5.675180196689268 12.03639056868854 7.208279885162786 18.33733431067133 50.80861737218254 7.563244456661175 5.511591334499364 40.6821013225322 5.519324005032368</data>
    </avgSatCells>
    <avgIntCells idx="1" type="struct" size="1 1">
      <data idx="1" type="double" size="1 9">242.5903350436747 229.3468099077634 237.7063786573819 215.393454889744 158.0136903671126 235.8401059800868 243.997330387554 176.7452821504189 240.6749746847095</data>
    </avgIntCells>
    <cornerRatioGrid idx="1" type="struct" size="1 1">
      <data idx="1" type="double" size="1 9">58 213 41 129 290 209 113 127 124</data>
    </cornerRatioGrid>
    <avgR idx="1" type="struct" size="1 1">
      <data idx="1" type="double" size="1 1">220.0748277156115</data>
    </avgR>
    <avgG idx="1" type="struct" size="1 1">
      <data idx="1" type="double" size="1 1">213.2217027156114</data>
    </avgG>
    <avgB idx="1" type="struct" size="1 1">
      <data idx="1" type="double" size="1 1">211.2833694391377</data>
    </avgB>
    <avgRCells idx="1" type="struct" size="1 1">
      <data idx="1" type="double" size="1 9">242.5837151059799 229.3293323559954 237.6918102131816 215.3511163032192 158.0101933296683 235.8217350803251 243.9819954585903 176.7375187946853 240.6515848906075</data>
    </avgRCells>
    <avgGCells idx="1" type="struct" size="1 1">
      <data idx="1" type="double" size="1 9">240.4612195345428 224.5939313420072 234.4090541200904 207.8422133650968 138.8115799279213 231.7205805998415 241.7707738807573 160.9166283101661 237.8539307741877</data>
    </avgGCells>
    <avgBCells idx="1" type="struct" size="1 1">
      <data idx="1" type="double" size="1 9">239.8099688473519 223.1130276097978 233.5398494288681 205.1813343717551 134.4818734347321 230.5144920896708 240.8645785387709 156.7291647488416 236.6699192979228</data>
    </avgBCells>
    <intEntropy idx="1" type="struct" size="1 1">
      <data idx="1" type="double" size="1 1">5.156186193389407</data>
    </intEntropy>
    <intVariance idx="1" type="struct" size="1 1">
      <data idx="1" type="double" size="1 1">3659.847350573063</data>
    </intVariance>
  </features>
</root>
