<?xml version="1.0"?>
<!-- Written on 16-Jun-2010 13:10:01 using the XML Toolbox for Matlab -->
<root xml_tb_version="3.1" idx="1" type="struct" size="1 1">
  <filename idx="1" type="char" size="1 30">Ruby_Rosetta_41_by_gsphoto.jpg</filename>
  <features idx="1" type="struct" size="1 1">
    <numFaces idx="1" type="struct" size="1 1">
      <data idx="1" type="double" size="1 1">0</data>
    </numFaces>
    <cornerRatio idx="1" type="struct" size="1 1">
      <data idx="1" type="double" size="1 1">0.0007715759849906192</data>
    </cornerRatio>
    <edgeRatio idx="1" type="struct" size="1 1">
      <data idx="1" type="double" size="1 1">0.2711632270168856</data>
    </edgeRatio>
    <gridEdgeRatio idx="1" type="struct" size="1 1">
      <data idx="1" type="double" size="1 9">0.250729592262153 0.2356999916618027 0.2427059617168396 0.2113107646126906 0.3094721921120653 0.3341344126823511 0.2795606334271433 0.2925820136934514 0.2852045367656429</data>
    </gridEdgeRatio>
    <medianHue idx="1" type="struct" size="1 1">
      <data idx="1" type="double" size="1 1">17</data>
    </medianHue>
    <avgSat idx="1" type="struct" size="1 1">
      <data idx="1" type="double" size="1 1">66.76616322701686</data>
    </avgSat>
    <avgInt idx="1" type="struct" size="1 1">
      <data idx="1" type="double" size="1 1">97.38489212007501</data>
    </avgInt>
    <medHueCells idx="1" type="struct" size="1 1">
      <data idx="1" type="double" size="1 9">17 17 17 17 17 17 17 17 17</data>
    </medHueCells>
    <avgSatCells idx="1" type="struct" size="1 1">
      <data idx="1" type="double" size="1 9">66.41355373968149 53.46614691903608 85.23291468895704 71.6599266238639 51.8812849162011 63.79674045448821 80.33940467155747 51.12764566995533 77.44352406439832</data>
    </avgSatCells>
    <avgIntCells idx="1" type="struct" size="1 1">
      <data idx="1" type="double" size="1 9">97.99126573834735 115.5212624030684 74.59923551896507 100.3114942049529 107.642291336613 99.50543957659514 87.37361919217463 110.4605995446497 82.76653498152162</data>
    </avgIntCells>
    <cornerRatioGrid idx="1" type="struct" size="1 1">
      <data idx="1" type="double" size="1 9">35 55 41 11 31 65 18 30 43</data>
    </cornerRatioGrid>
    <avgR idx="1" type="struct" size="1 1">
      <data idx="1" type="double" size="1 1">97.38466697936211</data>
    </avgR>
    <avgG idx="1" type="struct" size="1 1">
      <data idx="1" type="double" size="1 1">89.5534263602251</data>
    </avgG>
    <avgB idx="1" type="struct" size="1 1">
      <data idx="1" type="double" size="1 1">78.19505393996256</data>
    </avgB>
    <avgRCells idx="1" type="struct" size="1 1">
      <data idx="1" type="double" size="1 9">97.99126573834735 115.5204494288334 74.59910950560766 100.3113274410072 107.642291336613 99.50543957659514 87.37271270764813 110.4605995446497 82.76653498152162</data>
    </avgRCells>
    <avgGCells idx="1" type="struct" size="1 1">
      <data idx="1" type="double" size="1 9">90.16309513883095 107.6395605770032 66.871571386567 92.55440673726343 99.71022679896609 91.56512790355774 79.72990977316803 102.5560966354667 74.90603627713352</data>
    </avgGCells>
    <avgBCells idx="1" type="struct" size="1 1">
      <data idx="1" type="double" size="1 9">78.7610272659051 96.35716668056368 55.49327928760446 80.89618944384223 88.48651296589675 80.26240181459235 68.37469432498524 91.3609916519099 63.4807569771888</data>
    </avgBCells>
    <intEntropy idx="1" type="struct" size="1 1">
      <data idx="1" type="double" size="1 1">7.518134044109034</data>
    </intEntropy>
    <intVariance idx="1" type="struct" size="1 1">
      <data idx="1" type="double" size="1 1">2291.198928629562</data>
    </intVariance>
  </features>
</root>
