<?xml version="1.0"?>
<!-- Written on 16-Jun-2010 13:10:16 using the XML Toolbox for Matlab -->
<root xml_tb_version="3.1" idx="1" type="struct" size="1 1">
  <filename idx="1" type="char" size="1 33">Stella_Polaris_by_nyctopterus.png</filename>
  <features idx="1" type="struct" size="1 1">
    <numFaces idx="1" type="struct" size="1 1">
      <data idx="1" type="double" size="1 1">0</data>
    </numFaces>
    <cornerRatio idx="1" type="struct" size="1 1">
      <data idx="1" type="double" size="1 1">0.005436111111111111</data>
    </cornerRatio>
    <edgeRatio idx="1" type="struct" size="1 1">
      <data idx="1" type="double" size="1 1">0.2316666666666667</data>
    </edgeRatio>
    <gridEdgeRatio idx="1" type="struct" size="1 1">
      <data idx="1" type="double" size="1 9">0.2767211324921529 0.3054676740983362 0.272835820895522 0.1744395230828403 0.2173794369796899 0.1938557213930347 0.1710224438902743 0.2240897755610973 0.2488625</data>
    </gridEdgeRatio>
    <medianHue idx="1" type="struct" size="1 1">
      <data idx="1" type="double" size="1 1">0</data>
    </medianHue>
    <avgSat idx="1" type="struct" size="1 1">
      <data idx="1" type="double" size="1 1">0</data>
    </avgSat>
    <avgInt idx="1" type="struct" size="1 1">
      <data idx="1" type="double" size="1 1">26.23864722222224</data>
    </avgInt>
    <medHueCells idx="1" type="struct" size="1 1">
      <data idx="1" type="double" size="1 9">0 0 0 0 0 0 0 0 0</data>
    </medHueCells>
    <avgSatCells idx="1" type="struct" size="1 1">
      <data idx="1" type="double" size="1 9">0 0 0 0 0 0 0 0 0</data>
    </avgSatCells>
    <avgIntCells idx="1" type="struct" size="1 1">
      <data idx="1" type="double" size="1 9">29.01581866229948 20.20203223285071 26.34990024937657 31.22242900212157 21.89534869294424 28.49115960099749 29.85278606965174 19.61000000000002 29.43682499999998</data>
    </avgIntCells>
    <cornerRatioGrid idx="1" type="struct" size="1 1">
      <data idx="1" type="double" size="1 9">452 475 455 415 429 428 412 426 422</data>
    </cornerRatioGrid>
    <avgR idx="1" type="struct" size="1 1">
      <data idx="1" type="double" size="1 1">26.23864722222224</data>
    </avgR>
    <avgG idx="1" type="struct" size="1 1">
      <data idx="1" type="double" size="1 1">26.23864722222224</data>
    </avgG>
    <avgB idx="1" type="struct" size="1 1">
      <data idx="1" type="double" size="1 1">26.23864722222224</data>
    </avgB>
    <avgRCells idx="1" type="struct" size="1 1">
      <data idx="1" type="double" size="1 9">29.01581866229948 20.20203223285071 26.34990024937657 31.22242900212157 21.89534869294424 28.49115960099749 29.85278606965174 19.61000000000002 29.43682499999998</data>
    </avgRCells>
    <avgGCells idx="1" type="struct" size="1 1">
      <data idx="1" type="double" size="1 9">29.01581866229948 20.20203223285071 26.34990024937657 31.22242900212157 21.89534869294424 28.49115960099749 29.85278606965174 19.61000000000002 29.43682499999998</data>
    </avgGCells>
    <avgBCells idx="1" type="struct" size="1 1">
      <data idx="1" type="double" size="1 9">29.01581866229948 20.20203223285071 26.34990024937657 31.22242900212157 21.89534869294424 28.49115960099749 29.85278606965174 19.61000000000002 29.43682499999998</data>
    </avgBCells>
    <intEntropy idx="1" type="struct" size="1 1">
      <data idx="1" type="double" size="1 1">5.77047216852988</data>
    </intEntropy>
    <intVariance idx="1" type="struct" size="1 1">
      <data idx="1" type="double" size="1 1">341.9043419477691</data>
    </intVariance>
  </features>
</root>
