<?xml version="1.0"?>
<!-- Written on 16-Jun-2010 13:10:22 using the XML Toolbox for Matlab -->
<root xml_tb_version="3.1" idx="1" type="struct" size="1 1">
  <filename idx="1" type="char" size="1 24">Suphlatus_by_One_Vox.jpg</filename>
  <features idx="1" type="struct" size="1 1">
    <numFaces idx="1" type="struct" size="1 1">
      <data idx="1" type="double" size="1 1">1</data>
    </numFaces>
    <cornerRatio idx="1" type="struct" size="1 1">
      <data idx="1" type="double" size="1 1">0.0003976311336717428</data>
    </cornerRatio>
    <edgeRatio idx="1" type="struct" size="1 1">
      <data idx="1" type="double" size="1 1">0.07100888324873096</data>
    </edgeRatio>
    <gridEdgeRatio idx="1" type="struct" size="1 1">
      <data idx="1" type="double" size="1 9">0.006162369968340117 0.1139567314940449 0.03233199484809456 0.06364013266998342 0.1224559023066485 0.06273202515342069 0.09987088934457355 0.08312447786131998 0.05648639364909737</data>
    </gridEdgeRatio>
    <medianHue idx="1" type="struct" size="1 1">
      <data idx="1" type="double" size="1 1">17</data>
    </medianHue>
    <avgSat idx="1" type="struct" size="1 1">
      <data idx="1" type="double" size="1 1">97.98738790186125</data>
    </avgSat>
    <avgInt idx="1" type="struct" size="1 1">
      <data idx="1" type="double" size="1 1">76.27201353637899</data>
    </avgInt>
    <medHueCells idx="1" type="struct" size="1 1">
      <data idx="1" type="double" size="1 9">22 16 14 21 13 13 24 16 13</data>
    </medHueCells>
    <avgSatCells idx="1" type="struct" size="1 1">
      <data idx="1" type="double" size="1 9">99.05259686416402 94.97116689280877 82.08069415964155 107.724464797226 120.9331561887532 97.95921622237415 90.74882566861122 108.1423403288128 80.0081867104309</data>
    </avgSatCells>
    <avgIntCells idx="1" type="struct" size="1 1">
      <data idx="1" type="double" size="1 9">96.91487637569733 84.02406527966234 49.64549631654894 111.0999359264285 81.33378561736765 44.03987240829344 92.41029623456318 78.41834608682477 48.41490782794552</data>
    </avgIntCells>
    <cornerRatioGrid idx="1" type="struct" size="1 1">
      <data idx="1" type="double" size="1 9">0 65 0 15 44 16 10 22 16</data>
    </cornerRatioGrid>
    <avgR idx="1" type="struct" size="1 1">
      <data idx="1" type="double" size="1 1">76.16206218274107</data>
    </avgR>
    <avgG idx="1" type="struct" size="1 1">
      <data idx="1" type="double" size="1 1">65.32022208121823</data>
    </avgG>
    <avgB idx="1" type="struct" size="1 1">
      <data idx="1" type="double" size="1 1">48.81162648054145</data>
    </avgB>
    <avgRCells idx="1" type="struct" size="1 1">
      <data idx="1" type="double" size="1 9">96.91487637569733 83.91677973767527 49.58644717855243 111.0903625810343 81.27436680235185 43.55935292777397 92.2543753314645 78.35542465338284 48.35714285714284</data>
    </avgRCells>
    <avgGCells idx="1" type="struct" size="1 1">
      <data idx="1" type="double" size="1 9">88.09686416402833 71.26556610884971 41.58997873471558 93.73893788632594 63.45096487260665 36.48158274474063 85.61167512690353 67.12010379574211 40.39166444028855</data>
    </avgGCells>
    <avgBCells idx="1" type="struct" size="1 1">
      <data idx="1" type="double" size="1 9">62.5087064676617 54.61531358359719 34.96229209387103 65.82360922659431 47.57992235790745 30.26268322320954 60.77710432608533 48.66325100386393 34.13010953780392</data>
    </avgBCells>
    <intEntropy idx="1" type="struct" size="1 1">
      <data idx="1" type="double" size="1 1">7.106626409174424</data>
    </intEntropy>
    <intVariance idx="1" type="struct" size="1 1">
      <data idx="1" type="double" size="1 1">1579.381683853241</data>
    </intVariance>
  </features>
</root>
