<?xml version="1.0"?>
<!-- Written on 16-Jun-2010 13:10:23 using the XML Toolbox for Matlab -->
<root xml_tb_version="3.1" idx="1" type="struct" size="1 1">
  <filename idx="1" type="char" size="1 30">Sweet_Nothing_by_miss_mosh.jpg</filename>
  <features idx="1" type="struct" size="1 1">
    <numFaces idx="1" type="struct" size="1 1">
      <data idx="1" type="double" size="1 1">0</data>
    </numFaces>
    <cornerRatio idx="1" type="struct" size="1 1">
      <data idx="1" type="double" size="1 1">0.0003044164037854889</data>
    </cornerRatio>
    <edgeRatio idx="1" type="struct" size="1 1">
      <data idx="1" type="double" size="1 1">0.06454574132492114</data>
    </edgeRatio>
    <gridEdgeRatio idx="1" type="struct" size="1 1">
      <data idx="1" type="double" size="1 9">0.02537848830640604 0.09236244492147784 0.03848435205061565 0.09147271494746359 0.06127838662298028 0.0696672692351145 0.09390181900350232 0.06229522087899665 0.04555982374872884</data>
    </gridEdgeRatio>
    <medianHue idx="1" type="struct" size="1 1">
      <data idx="1" type="double" size="1 1">14</data>
    </medianHue>
    <avgSat idx="1" type="struct" size="1 1">
      <data idx="1" type="double" size="1 1">95.68176340694009</data>
    </avgSat>
    <avgInt idx="1" type="struct" size="1 1">
      <data idx="1" type="double" size="1 1">56.5753264984227</data>
    </avgInt>
    <medHueCells idx="1" type="struct" size="1 1">
      <data idx="1" type="double" size="1 9">20 11 7 7 103 11 75 90 98</data>
    </medHueCells>
    <avgSatCells idx="1" type="struct" size="1 1">
      <data idx="1" type="double" size="1 9">84.64970059880238 89.3871455202802 77.5510535532708 97.7660151395322 87.34150096034334 111.7841204383686 98.35337814936172 114.743390577336 99.51155236696412</data>
    </avgSatCells>
    <avgIntCells idx="1" type="struct" size="1 1">
      <data idx="1" type="double" size="1 9">42.46555473957745 63.78335781267655 49.19024686476104 111.1664924867247 77.81509151508305 54.70261834820927 24.91365382442661 37.83350751327534 48.29844085414079</data>
    </avgIntCells>
    <cornerRatioGrid idx="1" type="struct" size="1 1">
      <data idx="1" type="double" size="1 9">5 18 16 26 15 13 47 32 21</data>
    </cornerRatioGrid>
    <avgR idx="1" type="struct" size="1 1">
      <data idx="1" type="double" size="1 1">53.17730283911676</data>
    </avgR>
    <avgG idx="1" type="struct" size="1 1">
      <data idx="1" type="double" size="1 1">39.31138485804415</data>
    </avgG>
    <avgB idx="1" type="struct" size="1 1">
      <data idx="1" type="double" size="1 1">41.7228548895899</data>
    </avgB>
    <avgRCells idx="1" type="struct" size="1 1">
      <data idx="1" type="double" size="1 9">41.90745396000452 62.99627160772793 48.07364987007116 109.5891565924754 75.499971754604 53.94199807931308 17.38989944639023 29.10251666478362 41.11052423454975</data>
    </avgRCells>
    <avgGCells idx="1" type="struct" size="1 1">
      <data idx="1" type="double" size="1 9">32.0754010846232 44.74631397582193 37.13985707829627 79.96844989266745 48.47868884871763 25.95975031069935 20.04563043723872 27.89345836628629 38.09069596655743</data>
    </avgGCells>
    <avgBCells idx="1" type="struct" size="1 1">
      <data idx="1" type="double" size="1 9">33.6700796520167 45.59124675177948 38.79790419161676 79.47753078748164 54.74977403683199 31.00741441645013 23.78546209467857 30.6580188679245 38.47997401423569</data>
    </avgBCells>
    <intEntropy idx="1" type="struct" size="1 1">
      <data idx="1" type="double" size="1 1">6.265181833619587</data>
    </intEntropy>
    <intVariance idx="1" type="struct" size="1 1">
      <data idx="1" type="double" size="1 1">3602.595620138245</data>
    </intVariance>
  </features>
</root>
